graphics/__init__.py
graphics/app/Classifier.py
graphics/app/FaceDetector.py
graphics/app/FaceRecognition.py
graphics/app/FontWriter.py
graphics/app/Format.py
graphics/app/Graphics.py
graphics/app/ImageCrop.py
graphics/app/InsightFace.py
graphics/app/VideoCodec.py
graphics/app/VideoProcess.py
graphics/app/__init__.py
graphics/libs/__init__.py
graphics/libs/basnet.py
graphics/libs/common.py
graphics/libs/download.py
graphics/libs/face_align.py
graphics/libs/logger.py
graphics/libs/model_store.py
graphics/libs/network.py
graphics/libs/resnet_model.py
ai_graphics_gpu-0.1.15.dist-info/METADATA
ai_graphics_gpu-0.1.15.dist-info/WHEEL
ai_graphics_gpu-0.1.15.dist-info/top_level.txt
ai_graphics_gpu-0.1.15.dist-info/zip-safe
ai_graphics_gpu-0.1.15.dist-info/RECORD
