Metadata-Version: 2.1
Name: ai-graphics-gpu
Version: 0.1.15
Summary: AI Graphics Toolkit
Home-page: https://github.com/CachCheng/Python_Cookbook
Author: CachCheng
Author-email: tkggpdc2007@163.com
License: Apache-2.0
Platform: UNKNOWN
Requires-Dist: numpy
Requires-Dist: opencv-python
Requires-Dist: flask
Requires-Dist: tezign
Requires-Dist: mxnet-cu100
Requires-Dist: sklearn
Requires-Dist: scenedetect
Requires-Dist: moviepy
Requires-Dist: Pillow
Requires-Dist: torch (==1.1.0)
Requires-Dist: torchvision (==0.3.0)
